tfinterface/__coconut__.py
tfinterface/__init__.py
tfinterface/decorators.py
tfinterface/functions.py
tfinterface/layers.py
tfinterface/metrics.py
tfinterface/utils.py
tfinterface/version.py
tfinterface/base/__coconut__.py
tfinterface/base/__init__.py
tfinterface/base/base_class.py
tfinterface/base/inputs.py
tfinterface/base/model.py
tfinterface/reinforcement/__coconut__.py
tfinterface/reinforcement/__init__.py
tfinterface/reinforcement/dnq.py
tfinterface/reinforcement/expanded_state_env.py
tfinterface/reinforcement/experience_buffer.py
tfinterface/supervised/__coconut__.py
tfinterface/supervised/__init__.py
tfinterface/supervised/supervised_inputs.py
tfinterface/supervised/supervised_model.py
tfinterface/tests/__coconut__.py
tfinterface/tests/__init__.py
tfinterface/tests/test_supervised.py
tfinterface-0.0.13.dist-info/DESCRIPTION.rst
tfinterface-0.0.13.dist-info/METADATA
tfinterface-0.0.13.dist-info/RECORD
tfinterface-0.0.13.dist-info/WHEEL
tfinterface-0.0.13.dist-info/metadata.json
tfinterface-0.0.13.dist-info/top_level.txt
